odoo/addons/document_page_group/README.rst
odoo/addons/document_page_group/__init__.py
odoo/addons/document_page_group/__manifest__.py
odoo/addons/document_page_group/i18n/document_page_group.pot
odoo/addons/document_page_group/i18n/es.po
odoo/addons/document_page_group/i18n/it.po
odoo/addons/document_page_group/i18n/sl.po
odoo/addons/document_page_group/models/__init__.py
odoo/addons/document_page_group/models/document_page.py
odoo/addons/document_page_group/readme/CONTRIBUTORS.rst
odoo/addons/document_page_group/readme/DESCRIPTION.rst
odoo/addons/document_page_group/security/document_page_security.xml
odoo/addons/document_page_group/static/description/icon.png
odoo/addons/document_page_group/static/description/index.html
odoo/addons/document_page_group/tests/__init__.py
odoo/addons/document_page_group/tests/test_document_page_group.py
odoo/addons/document_page_group/views/document_page.xml
odoo14_addon_document_page_group-14.0.1.0.1.dev8.dist-info/METADATA
odoo14_addon_document_page_group-14.0.1.0.1.dev8.dist-info/WHEEL
odoo14_addon_document_page_group-14.0.1.0.1.dev8.dist-info/top_level.txt
odoo14_addon_document_page_group-14.0.1.0.1.dev8.dist-info/RECORD
